[
    {
        "Item_Name":  "InternalMonologue (Unverified)",
        "Type":  "Certificate",
        "Baseline_Rarity_Score":  100,
        "Baseline_Frequency":  "0%",
        "Baseline_Count":  0,
        "Malicious_Count":  3
    },
    {
        "Item_Name":  "IIS_Server_dll (Unverified)",
        "Type":  "Certificate",
        "Baseline_Rarity_Score":  100,
        "Baseline_Frequency":  "0%",
        "Baseline_Count":  0,
        "Malicious_Count":  3
    },
    {
        "Item_Name":  "SharpHostInfo (Unverified)",
        "Type":  "Certificate",
        "Baseline_Rarity_Score":  100,
        "Baseline_Frequency":  "0%",
        "Baseline_Count":  0,
        "Malicious_Count":  3
    },
    {
        "Item_Name":  "Rapid7 LLC; DigiCert Trusted G4 Code Signing RSA4096 SHA384 2021 CA1; DigiCert Trusted Root G4; DigiCert (Verified)",
        "Type":  "Certificate",
        "Baseline_Rarity_Score":  99.967,
        "Baseline_Frequency":  "0.033%",
        "Baseline_Count":  3,
        "Malicious_Count":  3
    },
    {
        "Item_Name":  "No Sig",
        "Type":  "Certificate",
        "Baseline_Rarity_Score":  60.0352,
        "Baseline_Frequency":  "39.9648%",
        "Baseline_Count":  3638,
        "Malicious_Count":  28
    }
]
